setup.py
django_mbills.egg-info/PKG-INFO
django_mbills.egg-info/SOURCES.txt
django_mbills.egg-info/dependency_links.txt
django_mbills.egg-info/top_level.txt
mbills/__init__.py
mbills/admin.py
mbills/helpers.py
mbills/models.py
mbills/migrations/0001_initial.py
mbills/migrations/__init__.py