Metadata-Version: 1.1
Name: django-mbills
Version: 0.1.0
Summary: Django implementation of the Hal MBills APIs.
Home-page: https://github.com/boris-savic/django-mbills
Author: Boris Savic
Author-email: boris70@gmail.com
License: MIT License
Platform: UNKNOWN
Classifier: Environment :: Web Environment
Classifier: Framework :: Django
Classifier: Intended Audience :: Developers
Classifier: Operating System :: OS Independent
Classifier: Programming Language :: Python
Classifier: Programming Language :: Python :: 3
Classifier: Programming Language :: Python :: 3.4
Classifier: Programming Language :: Python :: 3.5
